pygll.py
pygll-0.1.dist-info/METADATA
pygll-0.1.dist-info/WHEEL
pygll-0.1.dist-info/entry_points.txt
pygll-0.1.dist-info/top_level.txt
pygll-0.1.dist-info/RECORD
