Metadata-Version: 2.1
Name: pygll
Version: 0.1
Summary: Pygments syntax highlighting styles for dark and light backgrounds
Home-page: https://github.com/LivingLogic/LivingLogic.Python.PygLL
Author: Walter Doerwald
Author-email: walter@livinglogic.de
License: MIT
Download-URL: https://pypi.org/project/pygll/#files
Keywords: syntax highlighting,pygments style
Platform: UNKNOWN
Classifier: Development Status :: 4 - Beta
Classifier: Environment :: Plugins
Classifier: Intended Audience :: Developers
Classifier: License :: OSI Approved :: MIT License
Classifier: Operating System :: OS Independent
Classifier: Programming Language :: Python
Classifier: Programming Language :: Python :: 3
Classifier: Programming Language :: Python :: 3 :: Only
Classifier: Programming Language :: Python :: 3.8
Classifier: Programming Language :: Python :: 3.9
Classifier: Topic :: Software Development :: Documentation
Classifier: Topic :: Software Development :: Libraries :: Python Modules
Classifier: Topic :: Text Processing :: Filters
Classifier: Topic :: Utilities
Requires-Dist: pygments (>=2.0)
